StdCTL/StdCTLextension.py
StdCTL/__init__.py
StdCTL/test.py
StdCTL-0.1.3.dist-info/LICENSE
StdCTL-0.1.3.dist-info/METADATA
StdCTL-0.1.3.dist-info/WHEEL
StdCTL-0.1.3.dist-info/top_level.txt
StdCTL-0.1.3.dist-info/RECORD
