Metadata-Version: 2.1
Name: StdCTL
Version: 0.1.3
Summary: prompt for stdin/out
Home-page: https://github.com/xkcb1/prompt.git
Author: PureOPENS 2022[4]
Author-email: 3597974497@qq.com
License: UNKNOWN
Project-URL: Bug Tracker, https://github.com/xkcb1/prompt.git
Platform: UNKNOWN
Classifier: Programming Language :: Python :: 3
Classifier: License :: OSI Approved :: MIT License
Classifier: Operating System :: OS Independent
Requires-Python: >=3.6
License-File: LICENSE
